wa_socket/__init__.py
wa_socket/client.py
wa_socket/commands.py
wa_socket/events.py
wa_socket/process.py
wa_socket/session.py
wa_socket/utils.py
wa_socket/node/index.js
wa_socket/node/package-lock.json
wa_socket/node/package.json
wa_socket-0.1.7.dist-info/METADATA
wa_socket-0.1.7.dist-info/WHEEL
wa_socket-0.1.7.dist-info/top_level.txt
wa_socket-0.1.7.dist-info/RECORD
