Metadata-Version: 2.4
Name: wa-socket
Version: 0.1.7
Summary: Baileys-style WhatsApp Web socket for Python
Author-email: Ritik Sharma <ritiksharma19173@gmail.com>
License: MIT
Requires-Python: >=3.11
Requires-Dist: qrcode>=8.2
